pdffaroshuffle/__init__.py
pdffaroshuffle/utils.py
pdffaroshuffle-0.1.0.dist-info/METADATA
pdffaroshuffle-0.1.0.dist-info/WHEEL
pdffaroshuffle-0.1.0.dist-info/entry_points.txt
pdffaroshuffle-0.1.0.dist-info/RECORD
