Metadata-Version: 2.4
Name: pdffaroshuffle
Version: 0.1.0
Summary: Create a PDF from 2: first with even and second with odd pages.
Author-email: José Luis Segura Lucas <josel.segura@gmail.com>
License-Expression: GPL-3.0-or-later
Keywords: merge,pdf,pdfseparate,pdfunite
Requires-Python: >=3.13
Provides-Extra: lint
Requires-Dist: pre-commit; extra == 'lint'
